{
  "display": {
    "width": 1280,
    "height": 800,
    "target_fps": 30,
    "show_perf_panel": true,
    "target": ":1"
  },
  "detection": {
    "enabled": true,
    "confidence": 0.5,
    "detect_every_n": 1,
    "use_multi_core": false,
    "person_class_id": 0
  },
  "streams": {
    "max_streams": 4,
    "grid": "2x2",
    "watchdog_stall_s": 2.0,
    "min_capture_w": 1280,
    "min_capture_h": 720
  },
  "preprocessing": {
    "rotation_deg": 0.0,
    "exposure_delta": 0,
    "contrast": 1.0
  },
  "alarm": {
    "color_inside": [
      0,
      0,
      255
    ],
    "color_outside": [
      0,
      255,
      0
    ],
    "color_stale": [
      0,
      255,
      255
    ],
    "stale_threshold_s": 0.2
  },
  "recording": {
    "enabled": true,
    "save_dir": "/media/pi/6333-3864",
    "fallback_dir": "~/Videos",
    "segment_duration_min": 2,
    "codec": "mpp_h264",
    "storage_threshold_percent": 20
  }
}